svg_timeline/__init__.py
svg_timeline/json_serialize.py
svg_timeline/notation.py
svg_timeline/svg.py
svg_timeline/svg_style_defaults.py
svg_timeline/time_spacing.py
svg_timeline/timeline.py
svg_timeline/timeline_geometry.py
svg_timeline/vectors.py
svg_timeline-0.4.0.dist-info/licenses/LICENSE
svg_timeline-0.4.0.dist-info/WHEEL
svg_timeline-0.4.0.dist-info/METADATA
svg_timeline-0.4.0.dist-info/RECORD
