Metadata-Version: 2.4
Name: svg-timeline
Version: 0.4.0
Summary: A pure python library to create timeline plots
Keywords: timeline,svg,plotting,graph
Author: Timo Dreyer
Author-email: Timo Dreyer <dev@timodreyer.de>
License-Expression: MIT
License-File: LICENSE
Requires-Dist: ipython>=9.6.0 ; extra == 'ipython'
Requires-Python: >=3.11
Project-URL: Bug Tracker, https://github.com/TiDreyer/svg-timeline/issues
Project-URL: homepage, https://pypi.org/project/svg-timeline
Project-URL: repository, https://github.com/TiDreyer/svg-timeline
Provides-Extra: ipython
